Homework_1/ripple_carry_counter.v
module tff (q, clk, reset);

    output reg q;
    input clk, reset;

    always @(posedge reset or negedge clk)
    begin
        if (reset)
        begin
            q <= 1'b0;
        end 
        else
        begin
            q <= ~q;
        end
    end
endmodule

module ripple_carry_counter (q, clk, reset);
    output [7:0] q;
    input clk, reset;

    tff tff0(q[0], clk, reset);
    tff tff1(q[1], q[0], reset);
    tff tff2(q[2], q[1], reset);
    tff tff3(q[3], q[2], reset);
    tff tff4(q[4], q[3], reset);
    tff tff5(q[5], q[4], reset);
    tff tff6(q[6], q[5], reset);
    tff tff7(q[7], q[6], reset);

endmodule

module testbench;
    
    reg clk, reset;
    wire [7:0] q;

    ripple_carry_counter rcc (q,clk, reset);

    initial
    begin
        $dumpfile("dump.vcd");
        $dumpvars(1, testbench);
        
        clk = 1'b0;
        reset = 1'b0;
        #1 reset = 1'b0;
        
        reset = 1'b1;
        #1 reset = 1'b0;
        
        #500;
        $finish;

    end
   

    always #1 clk = ~clk;

endmodule

Homework_1/dump.vcd
$date
	Tue Feb  8 21:05:57 2022
$end
$version
	Icarus Verilog
$end
$timescale
	1s
$end
$scope module testbench $end
$var wire 8 ! q [7:0] $end
$var reg 1 " clk $end
$var reg 1 # reset $end
$upscope $end
$enddefinitions $end
#0
$dumpvars
0#
0"
bx !
$end
#1
b0 !
1"
1#
#2
b1 !
0"
0#
#3
1"
#4
b10 !
0"
#5
1"
#6
b11 !
0"
#7
1"
#8
b100 !
0"
#9
1"
#10
b101 !
0"
#11
1"
#12
b110 !
0"
#13
1"
#14
b111 !
0"
#15
1"
#16
b1000 !
0"
#17
1"
#18
b1001 !
0"
#19
1"
#20
b1010 !
0"
#21
1"
#22
b1011 !
0"
#23
1"
#24
b1100 !
0"
#25
1"
#26
b1101 !
0"
#27
1"
#28
b1110 !
0"
#29
1"
#30
b1111 !
0"
#31
1"
#32
b10000 !
0"
#33
1"
#34
b10001 !
0"
#35
1"
#36
b10010 !
0"
#37
1"
#38
b10011 !
0"
#39
1"
#40
b10100 !
0"
#41
1"
#42
b10101 !
0"
#43
1"
#44
b10110 !
0"
#45
1"
#46
b10111 !
0"
#47
1"
#48
b11000 !
0"
#49
1"
#50
b11001 !
0"
#51
1"
#52
b11010 !
0"
#53
1"
#54
b11011 !
0"
#55
1"
#56
b11100 !
0"
#57
1"
#58
b11101 !
0"
#59
1"
#60
b11110 !
0"
#61
1"
#62
b11111 !
0"
#63
1"
#64
b100000 !
0"
#65
1"
#66
b100001 !
0"
#67
1"
#68
b100010 !
0"
#69
1"
#70
b100011 !
0"
#71
1"
#72
b100100 !
0"
#73
1"
#74
b100101 !
0"
#75
1"
#76
b100110 !
0"
#77
1"
#78
b100111 !
0"
#79
1"
#80
b101000 !
0"
#81
1"
#82
b101001 !
0"
#83
1"
#84
b101010 !
0"
#85
1"
#86
b101011 !
0"
#87
1"
#88
b101100 !
0"
#89
1"
#90
b101101 !
0"
#91
1"
#92
b101110 !
0"
#93
1"
#94
b101111 !
0"
#95
1"
#96
b110000 !
0"
#97
1"
#98
b110001 !
0"
#99
1"
#100
b110010 !
0"
#101
1"
#102
b110011 !
0"
#103
1"
#104
b110100 !
0"
#105
1"
#106
b110101 !
0"
#107
1"
#108
b110110 !
0"
#109
1"
#110
b110111 !
0"
#111
1"
#112
b111000 !
0"
#113
1"
#114
b111001 !
0"
#115
1"
#116
b111010 !
0"
#117
1"
#118
b111011 !
0"
#119
1"
#120
b111100 !
0"
#121
1"
#122
b111101 !
0"
#123
1"
#124
b111110 !
0"
#125
1"
#126
b111111 !
0"
#127
1"
#128
b1000000 !
0"
#129
1"
#130
b1000001 !
0"
#131
1"
#132
b1000010 !
0"
#133
1"
#134
b1000011 !
0"
#135
1"
#136
b1000100 !
0"
#137
1"
#138
b1000101 !
0"
#139
1"
#140
b1000110 !
0"
#141
1"
#142
b1000111 !
0"
#143
1"
#144
b1001000 !
0"
#145
1"
#146
b1001001 !
0"
#147
1"
#148
b1001010 !
0"
#149
1"
#150
b1001011 !
0"
#151
1"
#152
b1001100 !
0"
#153
1"
#154
b1001101 !
0"
#155
1"
#156
b1001110 !
0"
#157
1"
#158
b1001111 !
0"
#159
1"
#160
b1010000 !
0"
#161
1"
#162
b1010001 !
0"
#163
1"
#164
b1010010 !
0"
#165
1"
#166
b1010011 !
0"
#167
1"
#168
b1010100 !
0"
#169
1"
#170
b1010101 !
0"
#171
1"
#172
b1010110 !
0"
#173
1"
#174
b1010111 !
0"
#175
1"
#176
b1011000 !
0"
#177
1"
#178
b1011001 !
0"
#179
1"
#180
b1011010 !
0"
#181
1"
#182
b1011011 !
0"
#183
1"
#184
b1011100 !
0"
#185
1"
#186
b1011101 !
0"
#187
1"
#188
b1011110 !
0"
#189
1"
#190
b1011111 !
0"
#191
1"
#192
b1100000 !
0"
#193
1"
#194
b1100001 !
0"
#195
1"
#196
b1100010 !
0"
#197
1"
#198
b1100011 !
0"
#199
1"
#200
b1100100 !
0"
#201
1"
#202
b1100101 !
0"
#203
1"
#204
b1100110 !
0"
#205
1"
#206
b1100111 !
0"
#207
1"
#208
b1101000 !
0"
#209
1"
#210
b1101001 !
0"
#211
1"
#212
b1101010 !
0"
#213
1"
#214
b1101011 !
0"
#215
1"
#216
b1101100 !
0"
#217
1"
#218
b1101101 !
0"
#219
1"
#220
b1101110 !
0"
#221
1"
#222
b1101111 !
0"
#223
1"
#224
b1110000 !
0"
#225
1"
#226
b1110001 !
0"
#227
1"
#228
b1110010 !
0"
#229
1"
#230
b1110011 !
0"
#231
1"
#232
b1110100 !
0"
#233
1"
#234
b1110101 !
0"
#235
1"
#236
b1110110 !
0"
#237
1"
#238
b1110111 !
0"
#239
1"
#240
b1111000 !
0"
#241
1"
#242
b1111001 !
0"
#243
1"
#244
b1111010 !
0"
#245
1"
#246
b1111011 !
0"
#247
1"
#248
b1111100 !
0"
#249
1"
#250
b1111101 !
0"
#251
1"
#252
b1111110 !
0"
#253
1"
#254
b1111111 !
0"
#255
1"
#256
b10000000 !
0"
#257
1"
#258
b10000001 !
0"
#259
1"
#260
b10000010 !
0"
#261
1"
#262
b10000011 !
0"
#263
1"
#264
b10000100 !
0"
#265
1"
#266
b10000101 !
0"
#267
1"
#268
b10000110 !
0"
#269
1"
#270
b10000111 !
0"
#271
1"
#272
b10001000 !
0"
#273
1"
#274
b10001001 !
0"
#275
1"
#276
b10001010 !
0"
#277
1"
#278
b10001011 !
0"
#279
1"
#280
b10001100 !
0"
#281
1"
#282
b10001101 !
0"
#283
1"
#284
b10001110 !
0"
#285
1"
#286
b10001111 !
0"
#287
1"
#288
b10010000 !
0"
#289
1"
#290
b10010001 !
0"
#291
1"
#292
b10010010 !
0"
#293
1"
#294
b10010011 !
0"
#295
1"
#296
b10010100 !
0"
#297
1"
#298
b10010101 !
0"
#299
1"
#300
b10010110 !
0"
#301
1"
#302
b10010111 !
0"
#303
1"
#304
b10011000 !
0"
#305
1"
#306
b10011001 !
0"
#307
1"
#308
b10011010 !
0"
#309
1"
#310
b10011011 !
0"
#311
1"
#312
b10011100 !
0"
#313
1"
#314
b10011101 !
0"
#315
1"
#316
b10011110 !
0"
#317
1"
#318
b10011111 !
0"
#319
1"
#320
b10100000 !
0"
#321
1"
#322
b10100001 !
0"
#323
1"
#324
b10100010 !
0"
#325
1"
#326
b10100011 !
0"
#327
1"
#328
b10100100 !
0"
#329
1"
#330
b10100101 !
0"
#331
1"
#332
b10100110 !
0"
#333
1"
#334
b10100111 !
0"
#335
1"
#336
b10101000 !
0"
#337
1"
#338
b10101001 !
0"
#339
1"
#340
b10101010 !
0"
#341
1"
#342
b10101011 !
0"
#343
1"
#344
b10101100 !
0"
#345
1"
#346
b10101101 !
0"
#347
1"
#348
b10101110 !
0"
#349
1"
#350
b10101111 !
0"
#351
1"
#352
b10110000 !
0"
#353
1"
#354
b10110001 !
0"
#355
1"
#356
b10110010 !
0"
#357
1"
#358
b10110011 !
0"
#359
1"
#360
b10110100 !
0"
#361
1"
#362
b10110101 !
0"
#363
1"
#364
b10110110 !
0"
#365
1"
#366
b10110111 !
0"
#367
1"
#368
b10111000 !
0"
#369
1"
#370
b10111001 !
0"
#371
1"
#372
b10111010 !
0"
#373
1"
#374
b10111011 !
0"
#375
1"
#376
b10111100 !
0"
#377
1"
#378
b10111101 !
0"
#379
1"
#380
b10111110 !
0"
#381
1"
#382
b10111111 !
0"
#383
1"
#384
b11000000 !
0"
#385
1"
#386
b11000001 !
0"
#387
1"
#388
b11000010 !
0"
#389
1"
#390
b11000011 !
0"
#391
1"
#392
b11000100 !
0"
#393
1"
#394
b11000101 !
0"
#395
1"
#396
b11000110 !
0"
#397
1"
#398
b11000111 !
0"
#399
1"
#400
b11001000 !
0"
#401
1"
#402
b11001001 !
0"
#403
1"
#404
b11001010 !
0"
#405
1"
#406
b11001011 !
0"
#407
1"
#408
b11001100 !
0"
#409
1"
#410
b11001101 !
0"
#411
1"
#412
b11001110 !
0"
#413
1"
#414
b11001111 !
0"
#415
1"
#416
b11010000 !
0"
#417
1"
#418
b11010001 !
0"
#419
1"
#420
b11010010 !
0"
#421
1"
#422
b11010011 !
0"
#423
1"
#424
b11010100 !
0"
#425
1"
#426
b11010101 !
0"
#427
1"
#428
b11010110 !
0"
#429
1"
#430
b11010111 !
0"
#431
1"
#432
b11011000 !
0"
#433
1"
#434
b11011001 !
0"
#435
1"
#436
b11011010 !
0"
#437
1"
#438
b11011011 !
0"
#439
1"
#440
b11011100 !
0"
#441
1"
#442
b11011101 !
0"
#443
1"
#444
b11011110 !
0"
#445
1"
#446
b11011111 !
0"
#447
1"
#448
b11100000 !
0"
#449
1"
#450
b11100001 !
0"
#451
1"
#452
b11100010 !
0"
#453
1"
#454
b11100011 !
0"
#455
1"
#456
b11100100 !
0"
#457
1"
#458
b11100101 !
0"
#459
1"
#460
b11100110 !
0"
#461
1"
#462
b11100111 !
0"
#463
1"
#464
b11101000 !
0"
#465
1"
#466
b11101001 !
0"
#467
1"
#468
b11101010 !
0"
#469
1"
#470
b11101011 !
0"
#471
1"
#472
b11101100 !
0"
#473
1"
#474
b11101101 !
0"
#475
1"
#476
b11101110 !
0"
#477
1"
#478
b11101111 !
0"
#479
1"
#480
b11110000 !
0"
#481
1"
#482
b11110001 !
0"
#483
1"
#484
b11110010 !
0"
#485
1"
#486
b11110011 !
0"
#487
1"
#488
b11110100 !
0"
#489
1"
#490
b11110101 !
0"
#491
1"
#492
b11110110 !
0"
#493
1"
#494
b11110111 !
0"
#495
1"
#496
b11111000 !
0"
#497
1"
#498
b11111001 !
0"
#499
1"
#500
b11111010 !
0"
#501
1"
#502
b11111011 !
0"
